xopr/__init__.py
xopr/_version.py
xopr/cf_units.py
xopr/geometry.py
xopr/matlab_attribute_utils.py
xopr/opr_access.py
xopr/opr_tools.py
xopr/ops_api.py
xopr/radar_util.py
xopr/stac_cache.py
xopr/util.py
xopr/bedmap/__init__.py
xopr/bedmap/catalog.py
xopr/bedmap/converter.py
xopr/bedmap/geometry.py
xopr/bedmap/query.py
xopr/bedmap/tests/__init__.py
xopr/bedmap/tests/test_bedmap.py
xopr/map/README.md
xopr/map/polar.html
xopr/stac/__init__.py
xopr/stac/catalog.py
xopr/stac/config.py
xopr/stac/geometry.py
xopr/stac/metadata.py
xopr/stac/tests/__init__.py
xopr/stac/tests/common.py
xopr/stac/tests/conftest.py
xopr/stac/tests/test_catalog.py
xopr/stac/tests/test_integration.py
xopr/stac/tests/test_metadata.py
xopr/stac/tests/test_stac_validation.py
xopr/tests/test_basic_load_data.py
xopr/tests/test_geometry.py
xopr/tests/test_matlab_char_encoding.py
xopr/tests/test_opr_access.py
xopr/tests/test_ops_api.py
xopr/tests/test_stac_cache.py
xopr/xarray_accessor/__init__.py
xopr/xarray_accessor/formatting_html.py
xopr/xarray_accessor/style.css
xopr/xarray_accessor/xopr_accessor.py
xopr-0.3.0.dist-info/METADATA
xopr-0.3.0.dist-info/WHEEL
xopr-0.3.0.dist-info/licenses/LICENSE
xopr-0.3.0.dist-info/RECORD
