Metadata-Version: 2.4
Name: xopr
Version: 0.3.0
Summary: Access Open Polar Radar data in the Python data ecosystem
License-File: LICENSE
Requires-Python: >=3.11
Requires-Dist: aiohttp
Requires-Dist: antimeridian>=0.4.3
Requires-Dist: dask[distributed]
Requires-Dist: duckdb>=1.0.0
Requires-Dist: fsspec
Requires-Dist: geopandas
Requires-Dist: geoviews
Requires-Dist: h5netcdf
Requires-Dist: h5py>=3.9
Requires-Dist: haversine>=2.8.0
Requires-Dist: hdf5storage
Requires-Dist: matplotlib
Requires-Dist: numpy
Requires-Dist: platformdirs
Requires-Dist: pyarrow
Requires-Dist: requests
Requires-Dist: rustac>=0.6.0
Requires-Dist: scipy
Requires-Dist: shapely
Requires-Dist: xarray>=2024.10.0
Provides-Extra: docs
Requires-Dist: coiled>=1.117.0; extra == 'docs'
Requires-Dist: dask[distributed]; extra == 'docs'
Requires-Dist: hvplot; extra == 'docs'
Requires-Dist: ipykernel; extra == 'docs'
Requires-Dist: jupyter; extra == 'docs'
Requires-Dist: jupyter-bokeh; extra == 'docs'
Requires-Dist: jupyterlab; extra == 'docs'
Requires-Dist: mystmd; extra == 'docs'
Requires-Dist: pdoc>=14.0.0; extra == 'docs'
Requires-Dist: rioxarray; extra == 'docs'
Requires-Dist: verde; extra == 'docs'
Provides-Extra: stac
Requires-Dist: omegaconf; extra == 'stac'
Requires-Dist: pyarrow; extra == 'stac'
Requires-Dist: pystac; extra == 'stac'
Requires-Dist: stac-asset; extra == 'stac'
Requires-Dist: stac-fastapi-geoparquet[serve]; extra == 'stac'
Requires-Dist: stac-geoparquet; extra == 'stac'
Provides-Extra: test
Requires-Dist: flake8; extra == 'test'
Requires-Dist: omegaconf; extra == 'test'
Requires-Dist: pyarrow; extra == 'test'
Requires-Dist: pystac; extra == 'test'
Requires-Dist: pytest; extra == 'test'
Requires-Dist: pytest-cov; extra == 'test'
Requires-Dist: stac-asset; extra == 'test'
Requires-Dist: stac-fastapi-geoparquet[serve]; extra == 'test'
Requires-Dist: stac-geoparquet; extra == 'test'
Requires-Dist: stac-validator; extra == 'test'
